{
  "points": [
    {
      "z1": 5596,
      "z2": 6747,
      "z3": 1802,
      "z4": 8319,
      "cls": "se"
    },
    {
      "z1": 5900,
      "z2": 7553,
      "z3": 1654,
      "z4": 7252,
      "cls": "se"
    },
    {
      "z1": 9112,
      "z2": 4220,
      "z3": 4249,
      "z4": 4279,
      "cls": "se"
    },
    {
      "z1": 6815,
      "z2": 8856,
      "z3": 8603,
      "z4": 694,
      "cls": "se"
    },
    {
      "z1": 5028,
      "z2": 4457,
      "z3": 5683,
      "z4": 4909,
      "cls": "se"
    },
    {
      "z1": 7884,
      "z2": 8338,
      "z3": 963,
      "z4": 6669,
      "cls": "se"
    },
    {
      "z1": 1802,
      "z2": 5502,
      "z3": 9194,
      "z4": 6549,
      "cls": "se"
    },
    {
      "z1": 7300,
      "z2": 4124,
      "z3": 2393,
      "z4": 9438,
      "cls": "se"
    },
    {
      "z1": 8675,
      "z2": 5591,
      "z3": 4952,
      "z4": 2698,
      "cls": "se"
    },
    {
      "z1": 7509,
      "z2": 5268,
      "z3": 9982,
      "z4": 1550,
      "cls": "se"
    },
    {
      "z1": 6124,
      "z2": 5013,
      "z3": 2255,
      "z4": 9648,
      "cls": "se"
    },
    {
      "z1": 9999,
      "z2": 5533,
      "z3": 1141,
      "z4": 8751,
      "cls": "se"
    },
    {
      "z1": 8333,
      "z2": 9088,
      "z3": 3459,
      "z4": 2678,
      "cls": "se"
    },
    {
      "z1": 7275,
      "z2": 4413,
      "z3": 9089,
      "z4": 2220,
      "cls": "se"
    },
    {
      "z1": 7521,
      "z2": 2020,
      "z3": 7003,
      "z4": 5396,
      "cls": "se"
    },
    {
      "z1": 230,
      "z2": 9042,
      "z3": 8135,
      "z4": 9605,
      "cls": "se"
    },
    {
      "z1": 9815,
      "z2": 3,
      "z3": 9926,
      "z4": 9897,
      "cls": "se"
    },
    {
      "z1": 6558,
      "z2": 7126,
      "z3": 4844,
      "z4": 2699,
      "cls": "se"
    },
    {
      "z1": 2631,
      "z2": 8823,
      "z3": 3905,
      "z4": 7323,
      "cls": "se"
    },
    {
      "z1": 7398,
      "z2": 6838,
      "z3": 4738,
      "z4": 2548,
      "cls": "se"
    },
    {
      "z1": 6365,
      "z2": 2064,
      "z3": 5195,
      "z4": 9148,
      "cls": "se"
    },
    {
      "z1": 4627,
      "z2": 4790,
      "z3": 6792,
      "z4": 4195,
      "cls": "se"
    },
    {
      "z1": 2003,
      "z2": 5308,
      "z3": 9815,
      "z4": 6258,
      "cls": "se"
    },
    {
      "z1": 675,
      "z2": 6961,
      "z3": 9610,
      "z4": 8087,
      "cls": "se"
    },
    {
      "z1": 2392,
      "z2": 9931,
      "z3": 7609,
      "z4": 3967,
      "cls": "se"
    },
    {
      "z1": 4700,
      "z2": 8680,
      "z3": 2326,
      "z4": 6642,
      "cls": "se"
    },
    {
      "z1": 6574,
      "z2": 3697,
      "z3": 3560,
      "z4": 7344,
      "cls": "se"
    },
    {
      "z1": 2862,
      "z2": 3756,
      "z3": 6875,
      "z4": 9454,
      "cls": "se"
    },
    {
      "z1": 8680,
      "z2": 5900,
      "z3": 1655,
      "z4": 6565,
      "cls": "se"
    },
    {
      "z1": 6533,
      "z2": 1343,
      "z3": 8666,
      "z4": 6645,
      "cls": "se"
    },
    {
      "z1": 3068,
      "z2": 6090,
      "z3": 8229,
      "z4": 4211,
      "cls": "se"
    },
    {
      "z1": 9710,
      "z2": 9607,
      "z3": 2032,
      "z4": 3978,
      "cls": "se"
    },
    {
      "z1": 4350,
      "z2": 7287,
      "z3": 4925,
      "z4": 4087,
      "cls": "se"
    },
    {
      "z1": 4582,
      "z2": 4409,
      "z3": 5075,
      "z4": 6111,
      "cls": "se"
    },
    {
      "z1": 2403,
      "z2": 6217,
      "z3": 9443,
      "z4": 4740,
      "cls": "se"
    },
    {
      "z1": 7104,
      "z2": 2860,
      "z3": 7234,
      "z4": 4257,
      "cls": "se"
    },
    {
      "z1": 7437,
      "z2": 6643,
      "z3": 3073,
      "z4": 4154,
      "cls": "se"
    },
    {
      "z1": 223,
      "z2": 9547,
      "z3": 9564,
      "z4": 7995,
      "cls": "se"
    },
    {
      "z1": 7432,
      "z2": 8517,
      "z3": 1607,
      "z4": 5444,
      "cls": "se"
    },
    {
      "z1": 8457,
      "z2": 6481,
      "z3": 3969,
      "z4": 3010,
      "cls": "se"
    },
    {
      "z1": 6281,
      "z2": 8295,
      "z3": 1666,
      "z4": 6283,
      "cls": "se"
    },
    {
      "z1": 9740,
      "z2": 8727,
      "z3": 575,
      "z4": 6921,
      "cls": "se"
    },
    {
      "z1": 2456,
      "z2": 4597,
      "z3": 7308,
      "z4": 7424,
      "cls": "se"
    },
    {
      "z1": 5518,
      "z2": 9363,
      "z3": 5904,
      "z4": 2080,
      "cls": "se"
    },
    {
      "z1": 3065,
      "z2": 7722,
      "z3": 3385,
      "z4": 8279,
      "cls": "se"
    },
    {
      "z1": 2504,
      "z2": 8508,
      "z3": 7825,
      "z4": 3929,
      "cls": "se"
    },
    {
      "z1": 1737,
      "z2": 9292,
      "z3": 5570,
      "z4": 6593,
      "cls": "se"
    },
    {
      "z1": 8680,
      "z2": 2290,
      "z3": 8308,
      "z4": 4004,
      "cls": "se"
    },
    {
      "z1": 8526,
      "z2": 3541,
      "z3": 5946,
      "z4": 3702,
      "cls": "se"
    },
    {
      "z1": 9734,
      "z2": 5381,
      "z3": 2355,
      "z4": 5511,
      "cls": "se"
    },
    {
      "z1": 1749,
      "z2": 5823,
      "z3": 6992,
      "z4": 7672,
      "cls": "se"
    },
    {
      "z1": 1958,
      "z2": 4167,
      "z3": 8862,
      "z4": 9981,
      "cls": "se"
    },
    {
      "z1": 6389,
      "z2": 9463,
      "z3": 3122,
      "z4": 3726,
      "cls": "se"
    },
    {
      "z1": 7157,
      "z2": 2972,
      "z3": 3757,
      "z4": 8116,
      "cls": "se"
    },
    {
      "z1": 1602,
      "z2": 5726,
      "z3": 7878,
      "z4": 7411,
      "cls": "se"
    },
    {
      "z1": 9176,
      "z2": 2572,
      "z3": 3884,
      "z4": 7404,
      "cls": "se"
    },
    {
      "z1": 7449,
      "z2": 940,
      "z3": 9934,
      "z4": 6623,
      "cls": "se"
    },
    {
      "z1": 4408,
      "z2": 4089,
      "z3": 5763,
      "z4": 6021,
      "cls": "se"
    },
    {
      "z1": 9872,
      "z2": 5957,
      "z3": 887,
      "z4": 9238,
      "cls": "se"
    },
    {
      "z1": 6856,
      "z2": 655,
      "z3": 9813,
      "z4": 8343,
      "cls": "se"
    },
    {
      "z1": 7108,
      "z2": 8697,
      "z3": 1188,
      "z4": 6494,
      "cls": "se"
    },
    {
      "z1": 9009,
      "z2": 2424,
      "z3": 3549,
      "z4": 9983,
      "cls": "se"
    },
    {
      "z1": 3235,
      "z2": 3186,
      "z3": 7857,
      "z4": 8209,
      "cls": "se"
    },
    {
      "z1": 2363,
      "z2": 5742,
      "z3": 5896,
      "z4": 7411,
      "cls": "se"
    },
    {
      "z1": 1645,
      "z2": 8843,
      "z3": 5041,
      "z4": 7936,
      "cls": "se"
    },
    {
      "z1": 6234,
      "z2": 3965,
      "z3": 5243,
      "z4": 4826,
      "cls": "se"
    },
    {
      "z1": 8360,
      "z2": 6932,
      "z3": 7882,
      "z4": 867,
      "cls": "se"
    },
    {
      "z1": 9829,
      "z2": 6704,
      "z3": 583,
      "z4": 9345,
      "cls": "se"
    },
    {
      "z1": 7875,
      "z2": 6695,
      "z3": 9491,
      "z4": 818,
      "cls": "se"
    },
    {
      "z1": 3727,
      "z2": 5277,
      "z3": 9806,
      "z4": 3811,
      "cls": "se"
    },
    {
      "z1": 8516,
      "z2": 2902,
      "z3": 3141,
      "z4": 9397,
      "cls": "se"
    },
    {
      "z1": 9475,
      "z2": 576,
      "z3": 6696,
      "z4": 9984,
      "cls": "se"
    },
    {
      "z1": 8026,
      "z2": 4358,
      "z3": 1985,
      "z4": 9802,
      "cls": "se"
    },
    {
      "z1": 7298,
      "z2": 3653,
      "z3": 6845,
      "z4": 3483,
      "cls": "se"
    },
    {
      "z1": 9519,
      "z2": 8519,
      "z3": 1872,
      "z4": 4386,
      "cls": "se"
    },
    {
      "z1": 8117,
      "z2": 2588,
      "z3": 4332,
      "z4": 6935,
      "cls": "se"
    },
    {
      "z1": 908,
      "z2": 8069,
      "z3": 9796,
      "z4": 6316,
      "cls": "se"
    },
    {
      "z1": 4029,
      "z2": 5172,
      "z3": 4815,
      "z4": 6237,
      "cls": "se"
    },
    {
      "z1": 5514,
      "z2": 4007,
      "z3": 3584,
      "z4": 8328,
      "cls": "se"
    },
    {
      "z1": 1914,
      "z2": 5147,
      "z3": 8428,
      "z4": 7067,
      "cls": "se"
    },
    {
      "z1": 5199,
      "z2": 5836,
      "z3": 2542,
      "z4": 8001,
      "cls": "se"
    },
    {
      "z1": 3101,
      "z2": 6845,
      "z3": 4884,
      "z4": 5965,
      "cls": "se"
    },
    {
      "z1": 4122,
      "z2": 9082,
      "z3": 5972,
      "z4": 3044,
      "cls": "se"
    },
    {
      "z1": 9332,
      "z2": 2104,
      "z3": 4243,
      "z4": 7983,
      "cls": "se"
    },
    {
      "z1": 7442,
      "z2": 8668,
      "z3": 8727,
      "z4": 510,
      "cls": "se"
    },
    {
      "z1": 1110,
      "z2": 9642,
      "z3": 5569,
      "z4": 8905,
      "cls": "se"
    },
    {
      "z1": 9231,
      "z2": 7332,
      "z3": 5562,
      "z4": 1480,
      "cls": "se"
    },
    {
      "z1": 3621,
      "z2": 5225,
      "z3": 5372,
      "z4": 6115,
      "cls": "se"
    },
    {
      "z1": 6160,
      "z2": 9108,
      "z3": 828,
      "z4": 9419,
      "cls": "se"
    },
    {
      "z1": 3162,
      "z2": 6275,
      "z3": 3921,
      "z4": 8447,
      "cls": "se"
    },
    {
      "z1": 5380,
      "z2": 2893,
      "z3": 5596,
      "z4": 7043,
      "cls": "se"
    },
    {
      "z1": 5848,
      "z2": 4652,
      "z3": 4477,
      "z4": 5136,
      "cls": "se"
    },
    {
      "z1": 7018,
      "z2": 2628,
      "z3": 8100,
      "z4": 4242,
      "cls": "se"
    },
    {
      "z1": 2487,
      "z2": 4058,
      "z3": 7171,
      "z4": 9498,
      "cls": "se"
    },
    {
      "z1": 5212,
      "z2": 6640,
      "z3": 3114,
      "z4": 5714,
      "cls": "se"
    },
    {
      "z1": 2898,
      "z2": 7145,
      "z3": 7505,
      "z4": 4068,
      "cls": "se"
    },
    {
      "z1": 4849,
      "z2": 9406,
      "z3": 5401,
      "z4": 2792,
      "cls": "se"
    },
    {
      "z1": 9126,
      "z2": 2401,
      "z3": 6859,
      "z4": 4377,
      "cls": "se"
    },
    {
      "z1": 7103,
      "z2": 4561,
      "z3": 9515,
      "z4": 2139,
      "cls": "se"
    },
    {
      "z1": 4270,
      "z2": 8155,
      "z3": 2753,
      "z4": 6647,
      "cls": "se"
    },
    {
      "z1": 9296,
      "z2": 2750,
      "z3": 4047,
      "z4": 6609,
      "cls": "se"
    },
    {
      "z1": 5481,
      "z2": 8106,
      "z3": 8622,
      "z4": 1392,
      "cls": "se"
    },
    {
      "z1": 3035,
      "z2": 3558,
      "z3": 9493,
      "z4": 6879,
      "cls": "se"
    },
    {
      "z1": 5959,
      "z2": 4971,
      "z3": 6485,
      "z4": 3216,
      "cls": "se"
    },
    {
      "z1": 546,
      "z2": 9207,
      "z3": 6889,
      "z4": 9447,
      "cls": "se"
    },
    {
      "z1": 3981,
      "z2": 2480,
      "z3": 9115,
      "z4": 7463,
      "cls": "se"
    },
    {
      "z1": 7922,
      "z2": 8840,
      "z3": 7776,
      "z4": 545,
      "cls": "se"
    },
    {
      "z1": 2816,
      "z2": 9214,
      "z3": 3229,
      "z4": 8610,
      "cls": "se"
    },
    {
      "z1": 6863,
      "z2": 6662,
      "z3": 6216,
      "z4": 1956,
      "cls": "se"
    },
    {
      "z1": 3722,
      "z2": 2347,
      "z3": 9919,
      "z4": 8582,
      "cls": "se"
    },
    {
      "z1": 8123,
      "z2": 3841,
      "z3": 4469,
      "z4": 4714,
      "cls": "se"
    },
    {
      "z1": 2174,
      "z2": 5079,
      "z3": 6293,
      "z4": 9110,
      "cls": "se"
    },
    {
      "z1": 2769,
      "z2": 4087,
      "z3": 8006,
      "z4": 7038,
      "cls": "se"
    },
    {
      "z1": 6695,
      "z2": 4536,
      "z3": 9023,
      "z4": 2366,
      "cls": "se"
    },
    {
      "z1": 7148,
      "z2": 5195,
      "z3": 2636,
      "z4": 6185,
      "cls": "se"
    },
    {
      "z1": 6162,
      "z2": 5062,
      "z3": 4238,
      "z4": 4738,
      "cls": "se"
    },
    {
      "z1": 5458,
      "z2": 8137,
      "z3": 4700,
      "z4": 3085,
      "cls": "se"
    },
    {
      "z1": 7048,
      "z2": 5654,
      "z3": 4679,
      "z4": 3360,
      "cls": "se"
    },
    {
      "z1": 2067,
      "z2": 5976,
      "z3": 8297,
      "z4": 5761,
      "cls": "se"
    },
    {
      "z1": 342,
      "z2": 9811,
      "z3": 9819,
      "z4": 7420,
      "cls": "se"
    },
    {
      "z1": 2163,
      "z2": 8219,
      "z3": 4748,
      "z4": 7203,
      "cls": "se"
    },
    {
      "z1": 4433,
      "z2": 7295,
      "z3": 3128,
      "z4": 6197,
      "cls": "se"
    },
    {
      "z1": 5203,
      "z2": 4478,
      "z3": 7934,
      "z4": 3502,
      "cls": "se"
    },
    {
      "z1": 8818,
      "z2": 1199,
      "z3": 7106,
      "z4": 6427,
      "cls": "se"
    },
    {
      "z1": 8334,
      "z2": 911,
      "z3": 7054,
      "z4": 7563,
      "cls": "se"
    },
    {
      "z1": 6152,
      "z2": 2103,
      "z3": 7784,
      "z4": 5766,
      "cls": "se"
    },
    {
      "z1": 2911,
      "z2": 6718,
      "z3": 3804,
      "z4": 9235,
      "cls": "se"
    },
    {
      "z1": 4640,
      "z2": 6214,
      "z3": 5203,
      "z4": 4176,
      "cls": "se"
    },
    {
      "z1": 4232,
      "z2": 5137,
      "z3": 5389,
      "z4": 5329,
      "cls": "se"
    },
    {
      "z1": 8484,
      "z2": 9817,
      "z3": 123,
      "z4": 9664,
      "cls": "se"
    },
    {
      "z1": 7279,
      "z2": 3583,
      "z3": 6688,
      "z4": 3640,
      "cls": "se"
    },
    {
      "z1": 8163,
      "z2": 3784,
      "z3": 4784,
      "z4": 4452,
      "cls": "se"
    },
    {
      "z1": 1249,
      "z2": 6468,
      "z3": 8304,
      "z4": 7161,
      "cls": "se"
    },
    {
      "z1": 8145,
      "z2": 1407,
      "z3": 6358,
      "z4": 6924,
      "cls": "se"
    },
    {
      "z1": 5570,
      "z2": 8203,
      "z3": 7925,
      "z4": 1466,
      "cls": "se"
    },
    {
      "z1": 6027,
      "z2": 5502,
      "z3": 3272,
      "z4": 5674,
      "cls": "se"
    },
    {
      "z1": 7107,
      "z2": 3999,
      "z3": 9775,
      "z4": 2546,
      "cls": "se"
    },
    {
      "z1": 6344,
      "z2": 8867,
      "z3": 3465,
      "z4": 3470,
      "cls": "se"
    },
    {
      "z1": 4057,
      "z2": 3942,
      "z3": 9494,
      "z4": 4735,
      "cls": "se"
    },
    {
      "z1": 9479,
      "z2": 3242,
      "z3": 5254,
      "z4": 4385,
      "cls": "se"
    },
    {
      "z1": 4207,
      "z2": 9602,
      "z3": 7779,
      "z4": 2168,
      "cls": "se"
    },
    {
      "z1": 9342,
      "z2": 5498,
      "z3": 6345,
      "z4": 1880,
      "cls": "se"
    },
    {
      "z1": 8462,
      "z2": 4010,
      "z3": 5201,
      "z4": 3777,
      "cls": "se"
    },
    {
      "z1": 1307,
      "z2": 6364,
      "z3": 6897,
      "z4": 8743,
      "cls": "se"
    },
    {
      "z1": 3265,
      "z2": 6660,
      "z3": 7367,
      "z4": 3954,
      "cls": "se"
    },
    {
      "z1": 389,
      "z2": 7864,
      "z3": 8280,
      "z4": 9674,
      "cls": "se"
    },
    {
      "z1": 5551,
      "z2": 2248,
      "z3": 5523,
      "z4": 9714,
      "cls": "se"
    },
    {
      "z1": 6490,
      "z2": 8423,
      "z3": 7575,
      "z4": 1094,
      "cls": "se"
    },
    {
      "z1": 8231,
      "z2": 3275,
      "z3": 8478,
      "z4": 2977,
      "cls": "se"
    },
    {
      "z1": 9322,
      "z2": 2412,
      "z3": 3541,
      "z4": 9518,
      "cls": "se"
    },
    {
      "z1": 8542,
      "z2": 7013,
      "z3": 9344,
      "z4": 591,
      "cls": "se"
    },
    {
      "z1": 6440,
      "z2": 8593,
      "z3": 5754,
      "z4": 1795,
      "cls": "se"
    },
    {
      "z1": 4394,
      "z2": 9487,
      "z3": 3889,
      "z4": 4436,
      "cls": "se"
    },
    {
      "z1": 1209,
      "z2": 7506,
      "z3": 6385,
      "z4": 8148,
      "cls": "se"
    },
    {
      "z1": 9089,
      "z2": 8044,
      "z3": 9514,
      "z4": 248,
      "cls": "se"
    },
    {
      "z1": 8193,
      "z2": 7887,
      "z3": 2473,
      "z4": 4032,
      "cls": "se"
    },
    {
      "z1": 6409,
      "z2": 8689,
      "z3": 1587,
      "z4": 6178,
      "cls": "se"
    },
    {
      "z1": 1520,
      "z2": 5474,
      "z3": 8955,
      "z4": 7449,
      "cls": "se"
    },
    {
      "z1": 9640,
      "z2": 6154,
      "z3": 2321,
      "z4": 4890,
      "cls": "se"
    },
    {
      "z1": 3768,
      "z2": 8708,
      "z3": 6799,
      "z4": 2983,
      "cls": "se"
    },
    {
      "z1": 7675,
      "z2": 5019,
      "z3": 3984,
      "z4": 4204,
      "cls": "se"
    },
    {
      "z1": 3335,
      "z2": 7454,
      "z3": 9758,
      "z4": 2997,
      "cls": "se"
    },
    {
      "z1": 4194,
      "z2": 4488,
      "z3": 4918,
      "z4": 6825,
      "cls": "se"
    },
    {
      "z1": 9359,
      "z2": 2362,
      "z3": 6344,
      "z4": 4720,
      "cls": "se"
    },
    {
      "z1": 3582,
      "z2": 2492,
      "z3": 9596,
      "z4": 8493,
      "cls": "se"
    },
    {
      "z1": 9302,
      "z2": 7041,
      "z3": 5802,
      "z4": 1448,
      "cls": "se"
    },
    {
      "z1": 4865,
      "z2": 2992,
      "z3": 5051,
      "z4": 9871,
      "cls": "se"
    },
    {
      "z1": 9375,
      "z2": 391,
      "z3": 8182,
      "z4": 8008,
      "cls": "se"
    },
    {
      "z1": 6702,
      "z2": 1096,
      "z3": 8809,
      "z4": 7098,
      "cls": "se"
    },
    {
      "z1": 8069,
      "z2": 9034,
      "z3": 240,
      "z4": 9708,
      "cls": "se"
    },
    {
      "z1": 9412,
      "z2": 272,
      "z3": 7774,
      "z4": 9760,
      "cls": "se"
    },
    {
      "z1": 8947,
      "z2": 6208,
      "z3": 9528,
      "z4": 819,
      "cls": "se"
    },
    {
      "z1": 7616,
      "z2": 4580,
      "z3": 9884,
      "z4": 1942,
      "cls": "se"
    },
    {
      "z1": 3228,
      "z2": 9806,
      "z3": 3543,
      "z4": 6477,
      "cls": "se"
    },
    {
      "z1": 3539,
      "z2": 3875,
      "z3": 7823,
      "z4": 5999,
      "cls": "se"
    },
    {
      "z1": 6230,
      "z2": 5918,
      "z3": 3023,
      "z4": 5479,
      "cls": "se"
    },
    {
      "z1": 1105,
      "z2": 6828,
      "z3": 6845,
      "z4": 9067,
      "cls": "se"
    },
    {
      "z1": 2270,
      "z2": 8140,
      "z3": 4741,
      "z4": 6978,
      "cls": "se"
    },
    {
      "z1": 8914,
      "z2": 1110,
      "z3": 6816,
      "z4": 6893,
      "cls": "se"
    },
    {
      "z1": 6822,
      "z2": 9639,
      "z3": 6001,
      "z4": 1410,
      "cls": "se"
    },
    {
      "z1": 7275,
      "z2": 8336,
      "z3": 4026,
      "z4": 2643,
      "cls": "se"
    },
    {
      "z1": 9597,
      "z2": 3500,
      "z3": 4361,
      "z4": 4922,
      "cls": "se"
    },
    {
      "z1": 8679,
      "z2": 4070,
      "z3": 2589,
      "z4": 7143,
      "cls": "se"
    },
    {
      "z1": 8405,
      "z2": 9113,
      "z3": 188,
      "z4": 9374,
      "cls": "se"
    },
    {
      "z1": 3974,
      "z2": 4196,
      "z3": 4616,
      "z4": 8991,
      "cls": "se"
    },
    {
      "z1": 6571,
      "z2": 8867,
      "z3": 2755,
      "z4": 4129,
      "cls": "se"
    },
    {
      "z1": 9520,
      "z2": 2855,
      "z3": 5244,
      "z4": 4891,
      "cls": "se"
    },
    {
      "z1": 3057,
      "z2": 8027,
      "z3": 9065,
      "z4": 3143,
      "cls": "se"
    },
    {
      "z1": 8595,
      "z2": 3474,
      "z3": 2715,
      "z4": 8464,
      "cls": "se"
    },
    {
      "z1": 4385,
      "z2": 7550,
      "z3": 5530,
      "z4": 3482,
      "cls": "se"
    },
    {
      "z1": 7765,
      "z2": 4638,
      "z3": 4860,
      "z4": 3688,
      "cls": "se"
    },
    {
      "z1": 8259,
      "z2": 1185,
      "z3": 7073,
      "z4": 6729,
      "cls": "se"
    },
    {
      "z1": 4754,
      "z2": 5802,
      "z3": 2820,
      "z4": 8183,
      "cls": "se"
    },
    {
      "z1": 2174,
      "z2": 6950,
      "z3": 8768,
      "z4": 4714,
      "cls": "se"
    },
    {
      "z1": 9401,
      "z2": 6125,
      "z3": 6195,
      "z4": 1624,
      "cls": "se"
    },
    {
      "z1": 5223,
      "z2": 9583,
      "z3": 3315,
      "z4": 4315,
      "cls": "se"
    },
    {
      "z1": 9828,
      "z2": 2374,
      "z3": 8107,
      "z4": 3817,
      "cls": "se"
    },
    {
      "z1": 9264,
      "z2": 1446,
      "z3": 9277,
      "z4": 4925,
      "cls": "se"
    },
    {
      "z1": 1109,
      "z2": 7863,
      "z3": 6038,
      "z4": 9170,
      "cls": "se"
    },
    {
      "z1": 7180,
      "z2": 9793,
      "z3": 3059,
      "z4": 3379,
      "cls": "se"
    }
  ],
  "statistics": {
    "p": [4],
    "card": [200],
    "supported": [200],
    "extreme": [200],
    "unsupported": [0],
    "min": [223, 3, 123, 248],
    "max": [9999, 9931, 9982, 9984],
    "width": [9776, 9928, 9859, 9736],
    "method": ["l"]
  }
}
